[
 {
  "id": 1,
  "userID": 9,
  "amount": 269918,
  "quantity": 8,
  "products": [
   {
    "name": "Home Theatre Sony Bdv-e4100",
    "image": "img-home-theater-sony.jpg",
    "finalPrice": 32990,
    "quantity": 1,
    "amount": 32990
   },
   {
    "name": "Heladera no frost Whirlpool WRM45A",
    "image": "img-heladera-whirpool.jpg",
    "finalPrice": 43110,
    "quantity": 3,
    "amount": 129330
   },
   {
    "name": "Teclado Apple Magic Inalámbrico",
    "image": "img-apple-magic-keyboard.jpg",
    "finalPrice": 11399,
    "quantity": 2,
    "amount": 22798
   },
   {
    "name": "Nikon Reflex D3500 - Kit",
    "image": "img-camara-nikon.jpg",
    "finalPrice": 42400,
    "quantity": 2,
    "amount": 84800
   }
  ]
 },
 {
  "id": 2,
  "userID": 9,
  "amount": 16622,
  "quantity": 7,
  "products": [
   {
    "name": "Cafetera Moulinex Dolce Gusto Edited",
    "image": "img-cafetera-moulinex.jpg",
    "finalPrice": 100,
    "quantity": 4,
    "amount": 400
   },
   {
    "name": "Mouse Inalámbrico Logitech M280",
    "image": "img-mouse-logitech.jpg",
    "finalPrice": 1080,
    "quantity": 2,
    "amount": 2160
   },
   {
    "name": "Bicicleta Mountain Bike Fierce Rodado 29",
    "image": "img-bicicleta-fierce.jpg",
    "finalPrice": 14062,
    "quantity": 1,
    "amount": 14062
   }
  ]
 }
]